nonosolaris/__init__.py
nonosolaris/__main__.py
nonosolaris/_settings.py
nonosolaris/ascii_art.py
nonosolaris/cli.py
nonosolaris/__pycache__/__init__.cpython-36.pyc
nonosolaris/__pycache__/__init__.cpython-37.pyc
nonosolaris/__pycache__/_settings.cpython-37.pyc
nonosolaris/__pycache__/ascii_art.cpython-37.pyc
nonosolaris/__pycache__/cli.cpython-36.pyc
nonosolaris/__pycache__/cli.cpython-37.pyc
nonosolaris/commands/__init__.py
nonosolaris/commands/cmd_address_book.py
nonosolaris/commands/cmd_cell.py
nonosolaris/commands/__pycache__/__init__.cpython-36.pyc
nonosolaris/commands/__pycache__/__init__.cpython-37.pyc
nonosolaris/commands/__pycache__/cmd_address_book.cpython-37.pyc
nonosolaris/commands/__pycache__/cmd_cell.cpython-37.pyc
nonosolaris/config/__init__.py
nonosolaris/config/settings.py
nonosolaris/config/__pycache__/__init__.cpython-36.pyc
nonosolaris/config/__pycache__/__init__.cpython-37.pyc
nonosolaris/config/__pycache__/settings.cpython-36.pyc
nonosolaris/config/__pycache__/settings.cpython-37.pyc
nonosolaris/models/__init__.py
nonosolaris/models/address_book.py
nonosolaris/models/cells.py
nonosolaris/models/pdfrw_utils.py
nonosolaris/models/personas.py
nonosolaris/models/__pycache__/__init__.cpython-37.pyc
nonosolaris/models/__pycache__/address_book.cpython-37.pyc
nonosolaris/models/__pycache__/cells.cpython-37.pyc
nonosolaris/models/__pycache__/pdfrw_utils.cpython-37.pyc
nonosolaris/models/__pycache__/personas.cpython-37.pyc
nonosolaris/schemas/nonosolaris.json
nonosolaris/templates/.~lock.page_annuaire_v1.0.odt#
nonosolaris/templates/cover_annuaire_v1.0.odt
nonosolaris/templates/cover_annuaire_v1.0.pdf
nonosolaris/templates/formulaire_annuaire_notice.odt
nonosolaris/templates/formulaire_annuaire_notice.pdf
nonosolaris/templates/formulaire_annuaire_v1.0.odt
nonosolaris/templates/formulaire_annuaire_v1.0.pdf
nonosolaris/templates/page_annuaire_v1.0.odt
nonosolaris/templates/page_annuaire_v1.0.pdf
nonosolaris-1.1.11.dist-info/AUTHORS.rst
nonosolaris-1.1.11.dist-info/LICENSE
nonosolaris-1.1.11.dist-info/METADATA
nonosolaris-1.1.11.dist-info/WHEEL
nonosolaris-1.1.11.dist-info/entry_points.txt
nonosolaris-1.1.11.dist-info/top_level.txt
nonosolaris-1.1.11.dist-info/RECORD
