Metadata-Version: 2.1
Name: nonosolaris
Version: 1.1.11
Summary: Nono, le petit robot d'assistance a l'entraide humaine
Home-page: https://github.com/numengo/python-nonosolaris
Author: Cedric ROMAN
Author-email: roman@numengo.com
License: GNU General Public License v3
Keywords: solaris,nono, contact book, annuaire, telegram
Platform: UNKNOWN
Classifier: Development Status :: 3 - Alpha
Classifier: Intended Audience :: Developers
Classifier: License :: OSI Approved :: GNU General Public License v3 (GPLv3)
Classifier: Operating System :: Unix
Classifier: Operating System :: POSIX
Classifier: Operating System :: Microsoft :: Windows
Classifier: Programming Language :: Python
Classifier: Programming Language :: Python :: 3.7
Classifier: Programming Language :: Python :: 3.8
Classifier: Programming Language :: Python :: 3.9
Classifier: Programming Language :: Python :: 3.10
Classifier: Programming Language :: Python :: 3.11
Classifier: Programming Language :: Python :: Implementation :: CPython
Classifier: Programming Language :: Python :: Implementation :: PyPy
Classifier: Topic :: Utilities
License-File: LICENSE
License-File: AUTHORS.rst
Requires-Dist: future
Requires-Dist: click
Requires-Dist: ngoschema (>=1.0.10)
Requires-Dist: reportlab
Requires-Dist: pdfrw
